AutoEnsembler/AutoEn.py
AutoEnsembler/__init__.py
AutoEnsembler-1.5.dist-info/Licence.txt
AutoEnsembler-1.5.dist-info/METADATA
AutoEnsembler-1.5.dist-info/WHEEL
AutoEnsembler-1.5.dist-info/top_level.txt
AutoEnsembler-1.5.dist-info/RECORD
