Metadata-Version: 2.1
Name: AutoEnsembler
Version: 1.5
Summary: This AutoEnsembler helps you to find the best Ensemble model for you
Home-page: UNKNOWN
Author: Nilesh Chilka
Author-email: nileshchilka1@gmail.com
License: MIT
Keywords: AUTOENSEMBLE,ENSEMBLE,MACHINE LEARNING
Platform: UNKNOWN
Classifier: License :: OSI Approved :: MIT License
Classifier: Programming Language :: Python :: 3.6
Classifier: Programming Language :: Python :: 3.7
Classifier: Programming Language :: Python :: 3.8
Requires-Dist: numpy
Requires-Dist: scikit-learn
Requires-Dist: xgboost
Requires-Dist: lightgbm
